jsontreeview/__init__.py
jsontreeview/treeviewer.py
jsontreeview-2.6.dist-info/LICENSE.txt
jsontreeview-2.6.dist-info/METADATA
jsontreeview-2.6.dist-info/WHEEL
jsontreeview-2.6.dist-info/top_level.txt
jsontreeview-2.6.dist-info/RECORD
