Metadata-Version: 2.1
Name: jsontreeview
Version: 2.6
Summary: A simple python program for viewing JSON data more clearly
Author: tk
License: UNKNOWN
Project-URL: Source, https://github.com/tksoftw/JsonTreeView
Platform: UNKNOWN
Requires-Python: >=3.7, <4
License-File: LICENSE.txt
